Metadata-Version: 2.4
Name: adafruit-circuitpython-ltr329-ltr303
Version: 3.0.12
Summary: Python driver for LTR-329/303 light sensors
Author-email: Adafruit Industries <circuitpython@adafruit.com>
License: MIT
Project-URL: Homepage, https://github.com/adafruit/Adafruit_CircuitPython_LTR329_LTR303
Keywords: adafruit,blinka,circuitpython,micropython,ltr329,LTR-329,LTR329,LTR-303,ltr303,LRT303,light,lux,sensor
Classifier: Intended Audience :: Developers
Classifier: Topic :: Software Development :: Libraries
Classifier: Topic :: Software Development :: Embedded Systems
Classifier: Topic :: System :: Hardware
Classifier: License :: OSI Approved :: MIT License
Classifier: Programming Language :: Python :: 3
License-File: LICENSE
Requires-Dist: Adafruit-Blinka
Requires-Dist: adafruit-circuitpython-busdevice
Requires-Dist: adafruit-circuitpython-register
Provides-Extra: optional
Requires-Dist: adafruit-circuitpython-debug-i2c; extra == "optional"
Dynamic: license-file
